langgraph/checkpoint/duckdb/__init__.py
langgraph/checkpoint/duckdb/aio.py
langgraph/checkpoint/duckdb/base.py
langgraph/checkpoint/duckdb/py.typed
langgraph/store/duckdb/__init__.py
langgraph/store/duckdb/aio.py
langgraph/store/duckdb/base.py
langgraph/store/duckdb/py.typed
langgraph_checkpoint_duckdb-2.0.2.dist-info/METADATA
langgraph_checkpoint_duckdb-2.0.2.dist-info/WHEEL
langgraph_checkpoint_duckdb-2.0.2.dist-info/RECORD
