Metadata-Version: 2.1
Name: langgraph-checkpoint-duckdb
Version: 2.0.2
Summary: Library with a DuckDB implementation of LangGraph checkpoint saver.
Home-page: https://www.github.com/langchain-ai/langgraph
License: MIT
Requires-Python: >=3.9.0,<4.0.0
Classifier: License :: OSI Approved :: MIT License
Classifier: Programming Language :: Python :: 3
Classifier: Programming Language :: Python :: 3.9
Classifier: Programming Language :: Python :: 3.10
Classifier: Programming Language :: Python :: 3.11
Classifier: Programming Language :: Python :: 3.12
Requires-Dist: duckdb (>=1.1.2)
Requires-Dist: langgraph-checkpoint (>=2.0.2,<3.0.0)
Project-URL: Repository, https://www.github.com/langchain-ai/langgraph
